<?xml version="1.0" encoding="utf-8" ?>
<c2layout>
    <name>Materi layout</name>
    <sid>823652669997428</sid>
    <event-sheet>Materi</event-sheet>
    <size>
        <width>1280</width>
        <height>720</height>
    </size>
    <margins>
        <horizontal>500</horizontal>
        <vertical>500</vertical>
    </margins>
    <unbounded-scrolling>0</unbounded-scrolling>
    <layers>
        <layer name="Layer 0" sid="687006084239263">
            <initially-visible>1</initially-visible>
            <background-color>255,255,255</background-color>
            <transparent>0</transparent>
            <parallax>
                <x>1</x>
                <y>1</y>
            </parallax>
            <zoom-rate>1</zoom-rate>
            <opacity>1</opacity>
            <force-own-texture>0</force-own-texture>
            <global>0</global>
            <use-render-cells>0</use-render-cells>
            <blend-mode>0</blend-mode>
            <effect-fallback>0</effect-fallback>
            <instances>
                <instance type="background_materi" uid="13">
                    <properties>
                        <initial-visibility>Visible</initial-visibility>
                        <initial-animation>Default</initial-animation>
                        <initial-frame>0</initial-frame>
                        <collisions>Enabled</collisions>
                    </properties>
                    <blend-mode>0</blend-mode>
                    <effect-fallback>0</effect-fallback>
                    <world>
                        <x>641</x>
                        <y>357</y>
                        <z>0</z>
                        <width>1280</width>
                        <height>720</height>
                        <depth>0</depth>
                        <hotspotX>0.5</hotspotX>
                        <hotspotY>0.5</hotspotY>
                        <angle>0</angle>
                        <opacity>1</opacity>
                    </world>
                </instance>
                <instance type="bangun_datar" uid="14">
                    <properties>
                        <initial-visibility>Visible</initial-visibility>
                        <initial-animation>Default</initial-animation>
                        <initial-frame>0</initial-frame>
                        <collisions>Enabled</collisions>
                    </properties>
                    <blend-mode>0</blend-mode>
                    <effect-fallback>0</effect-fallback>
                    <world>
                        <x>313.806518555</x>
                        <y>152.336425781</y>
                        <z>0</z>
                        <width>478.463287354</width>
                        <height>136.436798096</height>
                        <depth>0</depth>
                        <hotspotX>0.5</hotspotX>
                        <hotspotY>0.5</hotspotY>
                        <angle>0</angle>
                        <opacity>1</opacity>
                    </world>
                </instance>
                <instance type="persegi_panjang" uid="15">
                    <properties>
                        <initial-visibility>Visible</initial-visibility>
                        <initial-animation>Default</initial-animation>
                        <initial-frame>0</initial-frame>
                        <collisions>Enabled</collisions>
                    </properties>
                    <blend-mode>0</blend-mode>
                    <effect-fallback>0</effect-fallback>
                    <world>
                        <x>311.05770874</x>
                        <y>308.438781738</y>
                        <z>0</z>
                        <width>381.914306641</width>
                        <height>165.325057983</height>
                        <depth>0</depth>
                        <hotspotX>0.500097394</hotspotX>
                        <hotspotY>0.5</hotspotY>
                        <angle>0</angle>
                        <opacity>1</opacity>
                    </world>
                </instance>
                <instance type="P_materi" uid="16">
                    <properties>
                        <initial-visibility>Visible</initial-visibility>
                        <initial-animation>Default</initial-animation>
                        <initial-frame>0</initial-frame>
                        <collisions>Enabled</collisions>
                    </properties>
                    <blend-mode>0</blend-mode>
                    <effect-fallback>0</effect-fallback>
                    <world>
                        <x>901.811096191</x>
                        <y>419.092681885</y>
                        <z>0</z>
                        <width>625.250610352</width>
                        <height>558.085021973</height>
                        <depth>0</depth>
                        <hotspotX>0.5</hotspotX>
                        <hotspotY>0.501094103</hotspotY>
                        <angle>0</angle>
                        <opacity>1</opacity>
                    </world>
                </instance>
                <instance type="button_definisi" uid="17">
                    <properties>
                        <initial-visibility>Visible</initial-visibility>
                        <initial-animation>Default</initial-animation>
                        <initial-frame>0</initial-frame>
                        <collisions>Enabled</collisions>
                    </properties>
                    <blend-mode>0</blend-mode>
                    <effect-fallback>0</effect-fallback>
                    <world>
                        <x>719</x>
                        <y>134</y>
                        <z>0</z>
                        <width>167.213989258</width>
                        <height>84.628089905</height>
                        <depth>0</depth>
                        <hotspotX>0.50024426</hotspotX>
                        <hotspotY>0.5</hotspotY>
                        <angle>0</angle>
                        <opacity>1</opacity>
                    </world>
                </instance>
                <instance type="button_luas" uid="18">
                    <properties>
                        <initial-visibility>Visible</initial-visibility>
                        <initial-animation>Default</initial-animation>
                        <initial-frame>0</initial-frame>
                        <collisions>Enabled</collisions>
                    </properties>
                    <blend-mode>0</blend-mode>
                    <effect-fallback>0</effect-fallback>
                    <world>
                        <x>914</x>
                        <y>134</y>
                        <z>0</z>
                        <width>167.214004517</width>
                        <height>84.627998352</height>
                        <depth>0</depth>
                        <hotspotX>0.5</hotspotX>
                        <hotspotY>0.500535905</hotspotY>
                        <angle>0</angle>
                        <opacity>1</opacity>
                    </world>
                </instance>
                <instance type="button_keliling" uid="19">
                    <properties>
                        <initial-visibility>Visible</initial-visibility>
                        <initial-animation>Default</initial-animation>
                        <initial-frame>0</initial-frame>
                        <collisions>Enabled</collisions>
                    </properties>
                    <blend-mode>0</blend-mode>
                    <effect-fallback>0</effect-fallback>
                    <world>
                        <x>1108</x>
                        <y>134</y>
                        <z>0</z>
                        <width>167.214004517</width>
                        <height>84.627998352</height>
                        <depth>0</depth>
                        <hotspotX>0.5</hotspotX>
                        <hotspotY>0.500541687</hotspotY>
                        <angle>0</angle>
                        <opacity>1</opacity>
                    </world>
                </instance>
                <instance type="button_back" uid="20">
                    <properties>
                        <initial-visibility>Visible</initial-visibility>
                        <initial-animation>Default</initial-animation>
                        <initial-frame>0</initial-frame>
                        <collisions>Enabled</collisions>
                    </properties>
                    <blend-mode>0</blend-mode>
                    <effect-fallback>0</effect-fallback>
                    <world>
                        <x>60.632396698</x>
                        <y>48.34287262</y>
                        <z>0</z>
                        <width>63.464424133</width>
                        <height>59.497898102</height>
                        <depth>0</depth>
                        <hotspotX>0.5</hotspotX>
                        <hotspotY>0.5</hotspotY>
                        <angle>0</angle>
                        <opacity>1</opacity>
                    </world>
                </instance>
                <instance type="teks_definisi" uid="21">
                    <properties>
                        <text></text>
                        <initial-visibility>Visible</initial-visibility>
                        <font>Arial Rounded MT Bold,-19,400,0</font>
                        <color>0,0,0</color>
                        <horizontal-alignment>Left</horizontal-alignment>
                        <vertical-alignment>Top</vertical-alignment>
                        <hotspot>Top-left</hotspot>
                        <wrapping>Word</wrapping>
                        <line-height>0</line-height>
                    </properties>
                    <instance-variables>
                        <definisi>Persegi panjang adalah bangun datar dua dimensi yang memiliki empat sisi, di mana dua pasang sisi yang berlawanan memiliki panjang yang sama. Sisi-sisi yang berhadapan ini sejajar dan membentuk sudut siku-siku (90 derajat) di setiap pojoknya. Persegi panjang memiliki dua dimensi utama, yaitu panjang dan lebar.</definisi>
                    </instance-variables>
                    <behavior-instances>
                        <behavior-instance type="Timer" />
                    </behavior-instances>
                    <blend-mode>0</blend-mode>
                    <effect-fallback>0</effect-fallback>
                    <world>
                        <x>642</x>
                        <y>198</y>
                        <z>0</z>
                        <width>533</width>
                        <height>301</height>
                        <depth>0</depth>
                        <hotspotX>0</hotspotX>
                        <hotspotY>0</hotspotY>
                        <angle>0</angle>
                        <opacity>1</opacity>
                    </world>
                </instance>
                <instance type="teks_luas" uid="22">
                    <properties>
                        <text></text>
                        <initial-visibility>Visible</initial-visibility>
                        <font>Arial Rounded MT Bold,-19,400,0</font>
                        <color>0,0,0</color>
                        <horizontal-alignment>Left</horizontal-alignment>
                        <vertical-alignment>Top</vertical-alignment>
                        <hotspot>Top-left</hotspot>
                        <wrapping>Word</wrapping>
                        <line-height>0</line-height>
                    </properties>
                    <instance-variables>
                        <luas>Luas persegi panjang dihitung dengan rumus : &#x0A;Luas = panjang × lebar</luas>
                    </instance-variables>
                    <behavior-instances>
                        <behavior-instance type="Timer" />
                    </behavior-instances>
                    <blend-mode>0</blend-mode>
                    <effect-fallback>0</effect-fallback>
                    <world>
                        <x>639</x>
                        <y>198</y>
                        <z>0</z>
                        <width>533</width>
                        <height>301</height>
                        <depth>0</depth>
                        <hotspotX>0</hotspotX>
                        <hotspotY>0</hotspotY>
                        <angle>0</angle>
                        <opacity>1</opacity>
                    </world>
                </instance>
                <instance type="teks_keliling" uid="23">
                    <properties>
                        <text></text>
                        <initial-visibility>Visible</initial-visibility>
                        <font>Arial Rounded MT Bold,-19,400,0</font>
                        <color>0,0,0</color>
                        <horizontal-alignment>Left</horizontal-alignment>
                        <vertical-alignment>Top</vertical-alignment>
                        <hotspot>Top-left</hotspot>
                        <wrapping>Word</wrapping>
                        <line-height>0</line-height>
                    </properties>
                    <instance-variables>
                        <keliling>Keliling persegi panjang dihitung dengan rumus :&#x0A; &#x0A;Keliling = 2 × (panjang + lebar)</keliling>
                    </instance-variables>
                    <behavior-instances>
                        <behavior-instance type="Timer" />
                    </behavior-instances>
                    <blend-mode>0</blend-mode>
                    <effect-fallback>0</effect-fallback>
                    <world>
                        <x>641</x>
                        <y>197</y>
                        <z>0</z>
                        <width>533</width>
                        <height>301</height>
                        <depth>0</depth>
                        <hotspotX>0</hotspotX>
                        <hotspotY>0</hotspotY>
                        <angle>0</angle>
                        <opacity>1</opacity>
                    </world>
                </instance>
            </instances>
            <effects />
        </layer>
    </layers>
    <nonworld-instances />
    <effects />
</c2layout>
